{
  "atmospheric_02": {
    "sensor_id": "atmospheric_02",
    "timestamp": "2025-05-02T01:30:03.766760",
    "type": "atmospheric",
    "data": {
      "air_temp": 15.1,
      "humidity": 51.68,
      "co2": 672.9,
      "wind_speed": 2.9,
      "rainfall": 22.2
    }
  },
  "atmospheric_03": {
    "sensor_id": "atmospheric_03",
    "timestamp": "2025-05-02T01:30:03.772861",
    "type": "atmospheric",
    "data": {
      "air_temp": 17.1,
      "humidity": 11.97,
      "co2": 331.5,
      "wind_speed": 0.9,
      "rainfall": 49.1
    }
  },
  "threat_05": {
    "sensor_id": "threat_05",
    "timestamp": "2025-05-02T01:30:03.766760",
    "type": "threat",
    "data": {
      "unauthorized_access": 1,
      "jamming": 82.59,
      "tampering": 0,
      "spoofing": 0,
      "anomaly_score": 0.3
    }
  },
  "water_04": {
    "sensor_id": "water_04",
    "timestamp": "2025-05-02T01:30:03.771821",
    "type": "water",
    "data": {
      "flow_rate": 14.94,
      "water_level": 80.81,
      "salinity": 84.11,
      "ph": 8.41,
      "turbidity": 5.09
    }
  },
  "soil_01": {
    "sensor_id": "soil_01",
    "timestamp": "2025-05-02T01:30:03.771821",
    "type": "soil",
    "data": {
      "moisture": 61.77,
      "temperature": 12.4,
      "pH": 8.43,
      "nitrogen": 72.42,
      "phosphorus": 57.8
    }
  },
  "atmospheric_01": {
    "sensor_id": "atmospheric_01",
    "timestamp": "2025-05-02T01:30:03.766760",
    "type": "atmospheric",
    "data": {
      "air_temp": 28.5,
      "humidity": 57.81,
      "co2": 631.0,
      "wind_speed": 13.3,
      "rainfall": 37.1
    }
  },
  "water_02": {
    "sensor_id": "water_02",
    "timestamp": "2025-05-02T01:30:03.768770",
    "type": "water",
    "data": {
      "flow_rate": 55.8,
      "water_level": 88.35,
      "salinity": 45.49,
      "ph": 7.89,
      "turbidity": 66.29
    }
  },
  "soil_02": {
    "sensor_id": "soil_02",
    "timestamp": "2025-05-02T01:30:03.768770",
    "type": "soil",
    "data": {
      "moisture": 69.84,
      "temperature": 34.1,
      "pH": 7.37,
      "nitrogen": 72.95,
      "phosphorus": 28.22
    }
  },
  "soil_05": {
    "sensor_id": "soil_05",
    "timestamp": "2025-05-02T01:30:03.772861",
    "type": "soil",
    "data": {
      "moisture": 34.55,
      "temperature": 34.3,
      "pH": 6.88,
      "nitrogen": 49.3,
      "phosphorus": 12.94
    }
  },
  "plant_02": {
    "sensor_id": "plant_02",
    "timestamp": "2025-05-02T01:30:03.768770",
    "type": "plant",
    "data": {
      "leaf_moisture": 53.56,
      "chlorophyll": 44.68,
      "growth_rate": 56.57,
      "disease_risk": 0.64,
      "stem_diameter": 85.14
    }
  },
  "threat_02": {
    "sensor_id": "threat_02",
    "timestamp": "2025-05-02T01:30:03.768770",
    "type": "threat",
    "data": {
      "unauthorized_access": 1,
      "jamming": 47.91,
      "tampering": 1,
      "spoofing": 0,
      "anomaly_score": 0.57
    }
  },
  "water_03": {
    "sensor_id": "water_03",
    "timestamp": "2025-05-02T01:30:03.772861",
    "type": "water",
    "data": {
      "flow_rate": 8.65,
      "water_level": 90.18,
      "salinity": 19.5,
      "ph": 7.85,
      "turbidity": 25.95
    }
  },
  "soil_03": {
    "sensor_id": "soil_03",
    "timestamp": "2025-05-02T01:30:03.764750",
    "type": "soil",
    "data": {
      "moisture": 41.44,
      "temperature": 12.2,
      "pH": 8.4,
      "nitrogen": 12.45,
      "phosphorus": 96.61
    }
  },
  "atmospheric_05": {
    "sensor_id": "atmospheric_05",
    "timestamp": "2025-05-02T01:30:03.768770",
    "type": "atmospheric",
    "data": {
      "air_temp": 28.0,
      "humidity": 16.52,
      "co2": 666.2,
      "wind_speed": 13.2,
      "rainfall": 32.2
    }
  },
  "plant_01": {
    "sensor_id": "plant_01",
    "timestamp": "2025-05-02T01:30:03.772861",
    "type": "plant",
    "data": {
      "leaf_moisture": 51.64,
      "chlorophyll": 48.01,
      "growth_rate": 46.25,
      "disease_risk": 0.78,
      "stem_diameter": 10.36
    }
  },
  "plant_04": {
    "sensor_id": "plant_04",
    "timestamp": "2025-05-02T01:30:03.768770",
    "type": "plant",
    "data": {
      "leaf_moisture": 32.04,
      "chlorophyll": 40.05,
      "growth_rate": 18.61,
      "disease_risk": 0.88,
      "stem_diameter": 67.17
    }
  },
  "plant_05": {
    "sensor_id": "plant_05",
    "timestamp": "2025-05-02T01:30:03.770779",
    "type": "plant",
    "data": {
      "leaf_moisture": 16.54,
      "chlorophyll": 38.79,
      "growth_rate": 75.65,
      "disease_risk": 0.32,
      "stem_diameter": 31.5
    }
  },
  "water_01": {
    "sensor_id": "water_01",
    "timestamp": "2025-05-02T01:30:03.770779",
    "type": "water",
    "data": {
      "flow_rate": 31.21,
      "water_level": 88.52,
      "salinity": 14.4,
      "ph": 7.49,
      "turbidity": 37.28
    }
  },
  "atmospheric_04": {
    "sensor_id": "atmospheric_04",
    "timestamp": "2025-05-02T01:30:03.766760",
    "type": "atmospheric",
    "data": {
      "air_temp": 29.0,
      "humidity": 37.03,
      "co2": 396.3,
      "wind_speed": 10.6,
      "rainfall": 44.2
    }
  },
  "threat_01": {
    "sensor_id": "threat_01",
    "timestamp": "2025-05-02T01:30:03.772861",
    "type": "threat",
    "data": {
      "unauthorized_access": 1,
      "jamming": 86.48,
      "tampering": 0,
      "spoofing": 0,
      "anomaly_score": 0.76
    }
  },
  "threat_03": {
    "sensor_id": "threat_03",
    "timestamp": "2025-05-02T01:30:03.770779",
    "type": "threat",
    "data": {
      "unauthorized_access": 0,
      "jamming": 32.42,
      "tampering": 0,
      "spoofing": 0,
      "anomaly_score": 0.04
    }
  },
  "water_05": {
    "sensor_id": "water_05",
    "timestamp": "2025-05-02T01:30:03.771821",
    "type": "water",
    "data": {
      "flow_rate": 82.15,
      "water_level": 24.21,
      "salinity": 3.38,
      "ph": 7.29,
      "turbidity": 53.51
    }
  },
  "soil_04": {
    "sensor_id": "soil_04",
    "timestamp": "2025-05-02T01:30:03.771821",
    "type": "soil",
    "data": {
      "moisture": 21.11,
      "temperature": 11.2,
      "pH": 8.2,
      "nitrogen": 24.86,
      "phosphorus": 94.38
    }
  },
  "plant_03": {
    "sensor_id": "plant_03",
    "timestamp": "2025-05-02T01:30:03.766760",
    "type": "plant",
    "data": {
      "leaf_moisture": 68.28,
      "chlorophyll": 52.78,
      "growth_rate": 94.06,
      "disease_risk": 0.52,
      "stem_diameter": 37.81
    }
  },
  "threat_04": {
    "sensor_id": "threat_04",
    "timestamp": "2025-05-02T01:30:03.770779",
    "type": "threat",
    "data": {
      "unauthorized_access": 1,
      "jamming": 50.68,
      "tampering": 0,
      "spoofing": 0,
      "anomaly_score": 0.97
    }
  }
}